{
    "id": "aquaria/breeding",
    "title": "Guppy Breeding Basics",
    "description": "Learn how to breed guppies and raise the fry.",
    "image": "/assets/quests/guppy-breeding.jpg",
    "npc": "/assets/npc/vega.jpg",
    "start": "start",
    "requiresQuests": ["aquaria/guppy"],
    "dialogue": [
        {
            "id": "start",
            "text": "To breed guppies, select a healthy male and female and place them in a separate breeding tank with plenty of cover.",
            "options": [{ "text": "Pair selected", "next": "condition" }]
        },
        {
            "id": "condition",
            "text": "Feed them quality live or frozen foods for a week to condition them for spawning.",
            "options": [{ "text": "They're conditioned", "next": "cover" }]
        },
        {
            "id": "cover",
            "text": "Floating plants give the fry a place to hide. Maintain warm, clean water between 24 and 28 degrees Celsius.",
            "options": [{ "text": "Plants added", "next": "fry" }]
        },
        {
            "id": "fry",
            "text": "After a few days you'll notice tiny fry swimming near the surface. Feed them powdered food or baby brine shrimp.",
            "options": [{ "text": "They're growing", "next": "raise" }]
        },
        {
            "id": "raise",
            "text": "Keep the adults separated so they don't eat the fry. Frequent small water changes help the babies grow quickly.",
            "options": [{ "text": "They're thriving", "next": "finish" }]
        },
        {
            "id": "finish",
            "text": "Soon your young guppies will be large enough to join the main tank or trade with friends.",
            "options": [{ "type": "finish", "text": "Can't wait!" }]
        }
    ]
}
