{
  "id": "OUT-2026-01-15-process-edit-404",
  "date": "2026-01-15",
  "component": "frontend/processes",
  "rootCause": "The /processes/{id}/edit route was missing, so custom process edit links returned a 404.",
  "resolution": "Added the missing edit route and shared create/edit process form logic, plus an end-to-end regression test for edit persistence.",
  "references": [
    "frontend/src/pages/processes/[processId]/edit.astro",
    "frontend/src/pages/processes/svelte/EditProcess.svelte",
    "frontend/src/components/svelte/ProcessForm.svelte",
    "frontend/e2e/process-edit.spec.ts",
    "https://staging.democratized.space/processes/8536efb6-fb4d-46ba-a52a-b13aaf75231e/edit"
  ]
}
