{
    "id": "programming/moving-avg-temp",
    "title": "Compute Moving Average Temperature",
    "description": "Add a moving average to your temperature analysis script.",
    "image": "/assets/quests/programming_moving_average_temperature.jpg",
    "npc": "/assets/npc/orion.jpg",
    "start": "start",
    "dialogue": [
        {
            "id": "start",
            "text": "Your average gives a big picture. Let's watch trends with a moving window.",
            "options": [
                {
                    "type": "goto",
                    "goto": "window",
                    "text": "Let's smooth it out.",
                    "requiresItems": [
                        { "id": "d06c9f8d-6553-4f3c-9e10-05e1cf33a6b8", "count": 1 },
                        { "id": "50360fd0-e296-4ef8-a3a9-00e049318166", "count": 1 },
                        { "id": "b6fc1ed6-f399-4fdb-9f9d-3913f893f43d", "count": 1 }
                    ]
                }
            ]
        },
        {
            "id": "window",
            "text": "Pick a window, calculate rolling averages, and check how much they lag behind the raw line before you publish.",
            "options": [
                {
                    "type": "process",
                    "process": "calculate-moving-average-series",
                    "text": "Generate the rolling series"
                },
                {
                    "type": "goto",
                    "goto": "compare",
                    "text": "Smoothing dialed in",
                    "requiresItems": [{ "id": "b3a07c4d-36ad-427b-803a-dd531c62f5a2", "count": 1 }]
                }
            ]
        },
        {
            "id": "compare",
            "text": "Overlay the moving average on your dashboard and update the JSON stats so downstream consumers see the smoothed trend too.",
            "options": [
                {
                    "type": "goto",
                    "goto": "finish",
                    "text": "Moving average deployed",
                    "requiresItems": [{ "id": "b3a07c4d-36ad-427b-803a-dd531c62f5a2", "count": 1 }]
                }
            ]
        },
        {
            "id": "finish",
            "text": "Nice! The moving average reveals trends in real time.",
            "options": [
                {
                    "type": "finish",
                    "text": "Data looks smoother."
                }
            ]
        }
    ],
    "rewards": [],
    "requiresQuests": ["programming/avg-temp"],
    "hardening": {
        "passes": 2,
        "score": 90,
        "emoji": "✅",
        "history": [
            {
                "task": "codex-hardening-2026-01-04",
                "date": "2026-01-04",
                "score": 88
            },
            {
                "task": "codex-hardening-2026-01-06",
                "date": "2026-01-06",
                "score": 90
            }
        ]
    }
}
